electricore/__init__.py
electricore/api/README.md
electricore/api/__init__.py
electricore/api/config.py
electricore/api/main.py
electricore/api/models.py
electricore/api/security.py
electricore/api/services/__init__.py
electricore/api/services/duckdb_service.py
electricore/config/database.yaml
electricore/config/turpe_rules.csv
electricore/core/__init__.py
electricore/core/_optional.py
electricore/core/loaders/__init__.py
electricore/core/loaders/duckdb/__init__.py
electricore/core/loaders/duckdb/config.py
electricore/core/loaders/duckdb/expressions.py
electricore/core/loaders/duckdb/helpers.py
electricore/core/loaders/duckdb/query.py
electricore/core/loaders/duckdb/registry.py
electricore/core/loaders/duckdb/sql.py
electricore/core/loaders/duckdb/transforms.py
electricore/core/loaders/odoo/__init__.py
electricore/core/loaders/odoo/config.py
electricore/core/loaders/odoo/helpers.py
electricore/core/loaders/odoo/query.py
electricore/core/loaders/odoo/reader.py
electricore/core/loaders/odoo/transforms.py
electricore/core/loaders/parquet.py
electricore/core/models/__init__.py
electricore/core/models/aggregates.py
electricore/core/models/historique_perimetre.py
electricore/core/models/odoo/__init__.py
electricore/core/models/odoo/commande.py
electricore/core/models/odoo/facture.py
electricore/core/models/periode_abonnement.py
electricore/core/models/periode_energie.py
electricore/core/models/periode_meta.py
electricore/core/models/releve_index.py
electricore/core/pipelines/__init__.py
electricore/core/pipelines/abonnements.py
electricore/core/pipelines/energie.py
electricore/core/pipelines/facturation.py
electricore/core/pipelines/orchestration.py
electricore/core/pipelines/perimetre.py
electricore/core/pipelines/turpe.py
electricore/core/writers/__init__.py
electricore/core/writers/odoo.py
electricore/etl/.dlt/config.toml
electricore/etl/.gitignore
electricore/etl/README.md
electricore/etl/config/__init__.py
electricore/etl/config/flux.yaml
electricore-1.3.4.dist-info/LICENSE
electricore-1.3.4.dist-info/METADATA
electricore-1.3.4.dist-info/WHEEL
electricore-1.3.4.dist-info/RECORD
