Metadata-Version: 2.3
Name: electricore
Version: 1.3.4
Summary: Moteur de traitement données énergétiques françaises - Architecture Polars/DuckDB pour flux Enedis
License: GPLv3
Keywords: energy,electricity,enedis,polars,duckdb,etl,turpe,linky,grid,data-processing
Author: Virgile
Requires-Python: >=3.12
Classifier: Development Status :: 5 - Production/Stable
Classifier: Intended Audience :: Developers
Classifier: Intended Audience :: Science/Research
Classifier: License :: OSI Approved :: GNU General Public License v3 (GPLv3)
Classifier: Operating System :: OS Independent
Classifier: Programming Language :: Python :: 3
Classifier: Programming Language :: Python :: 3.12
Classifier: Programming Language :: Python :: 3.13
Classifier: Programming Language :: Python :: 3.14
Classifier: Topic :: Scientific/Engineering
Classifier: Topic :: Software Development :: Libraries :: Python Modules
Classifier: Topic :: Utilities
Classifier: Typing :: Typed
Provides-Extra: all
Provides-Extra: api
Provides-Extra: core
Provides-Extra: etl
Provides-Extra: validation
Provides-Extra: viz
Requires-Dist: altair (>=5.5.0,<6.0.0) ; extra == "viz"
Requires-Dist: dlt[filesystem] (>=1.16.0,<2.0.0) ; extra == "etl"
Requires-Dist: duckdb (>=1.3.2,<2.0.0) ; extra == "etl"
Requires-Dist: electricore[api,core,etl,validation,viz] ; extra == "all"
Requires-Dist: fastapi (>=0.116.1,<0.117.0) ; extra == "api"
Requires-Dist: lxml (>=6.0.2,<7.0.0) ; extra == "etl"
Requires-Dist: marimo (>=0.16.4) ; extra == "viz"
Requires-Dist: pandera[polars] (>=0.24.0) ; extra == "validation"
Requires-Dist: paramiko (>=4.0.0,<5.0.0) ; extra == "etl"
Requires-Dist: plotly (>=6.2.0) ; extra == "viz"
Requires-Dist: polars (>=1.0.0,<2.0.0) ; extra == "core"
Requires-Dist: pyarrow (>=21.0.0,<22.0.0) ; extra == "viz"
Requires-Dist: pycryptodome (>=3.23.0,<4.0.0) ; extra == "etl"
Requires-Dist: uvicorn (>=0.35.0,<0.36.0) ; extra == "api"
Requires-Dist: vegafusion (>=2.0.3,<3.0.0) ; extra == "viz"
Requires-Dist: vl-convert-python (>=1.8.0,<2.0.0) ; extra == "viz"
Project-URL: Changelog, https://github.com/Energie-De-Nantes/electricore/blob/main/CHANGELOG.md
Project-URL: Documentation, https://github.com/Energie-De-Nantes/electricore/blob/main/README.md
Project-URL: Homepage, https://github.com/Energie-De-Nantes/electricore
Project-URL: Issues, https://github.com/Energie-De-Nantes/electricore/issues
Project-URL: Repository, https://github.com/Energie-De-Nantes/electricore
